jsonexussync_client/RestClient.py
jsonexussync_client/__init__.py
jsonexussync_client-1.0.2.dist-info/METADATA
jsonexussync_client-1.0.2.dist-info/WHEEL
jsonexussync_client-1.0.2.dist-info/top_level.txt
jsonexussync_client-1.0.2.dist-info/RECORD
