Metadata-Version: 2.1
Name: jsonexussync-client
Version: 1.0.2
Summary: client library of client JSONexusSync
Home-page: https://github.com/rakibma7254/jsonexussync-client
Author: Rakib Hossain
Author-email: rakib4ggp@gmail.com
License: MIT
Keywords: remote-database
Classifier: License :: OSI Approved :: MIT License
Classifier: Programming Language :: Python :: 3
Classifier: Programming Language :: Python :: 3.6
Requires-Dist: websockets
Requires-Dist: requests
